ncorpos_utilidades/__init__.py
ncorpos_utilidades/_version.py
ncorpos_utilidades/api.py
ncorpos_utilidades/_core/_core.cpython-311-x86_64-linux-gnu.so
ncorpos_utilidades/_core/libutilidades.so
ncorpos_utilidades_py.libs/libblas-fe34f726.so.3.8.0
ncorpos_utilidades_py.libs/libgfortran-83c28eba.so.5.0.0
ncorpos_utilidades_py.libs/liblapack-31d7d384.so.3.8.0
ncorpos_utilidades_py.libs/libopenblas-r0-11edc3fa.3.15.so
ncorpos_utilidades_py.libs/libquadmath-2284e583.so.0.0.0
ncorpos_utilidades_py-1.0.1.dist-info/METADATA
ncorpos_utilidades_py-1.0.1.dist-info/WHEEL
ncorpos_utilidades_py-1.0.1.dist-info/RECORD
ncorpos_utilidades_py-1.0.1.dist-info/licenses/LICENSE
ncorpos_utilidades_py-1.0.1.dist-info/sboms/auditwheel.cdx.json
