Metadata-Version: 2.2
Name: ncorpos-utilidades-py
Version: 1.0.1
Summary: Utilidades para problemas de N-corpos via Fortran.
Author: potalej
Requires-Dist: numpy
